{
  "warnings": [
    {
      "file": "/Users/d041771/git/npsapi-swift/Sources/NatParkSwiftKit/Model/Alert.swift",
      "line": 12,
      "symbol": "RequestableAlertField.void",
      "symbol_kind": "source.lang.swift.decl.enumelement",
      "warning": "undocumented"
    },
    {
      "file": "/Users/d041771/git/npsapi-swift/Sources/NatParkSwiftKit/Model/Asset.swift",
      "line": 12,
      "symbol": "RequestableAssetField.void",
      "symbol_kind": "source.lang.swift.decl.enumelement",
      "warning": "undocumented"
    },
    {
      "file": "/Users/d041771/git/npsapi-swift/Sources/NatParkSwiftKit/Model/NewsRelease.swift",
      "line": 12,
      "symbol": "RequestableNewsReleaseField.void",
      "symbol_kind": "source.lang.swift.decl.enumelement",
      "warning": "undocumented"
    },
    {
      "file": "/Users/d041771/git/npsapi-swift/Sources/NatParkSwiftKit/Model/VisitorCenter.swift",
      "line": 13,
      "symbol": "RequestableVisitorCenterField.void",
      "symbol_kind": "source.lang.swift.decl.enumelement",
      "warning": "undocumented"
    }
  ],
  "source_directory": "/Users/d041771/git/npsapi-swift"
}